ax/__init__.py
ax/cli/__init__.py
ax/cli/commands.py
ax/cli/main.py
ax/core/__init__.py
ax/core/ai_pipeline.py
ax/core/cache_service.py
ax/core/fix_executor.py
ax/core/hybrid_pipeline.py
ax/core/language_detector.py
ax/core/parser.py
ax/core/pattern_learner.py
ax/core/pipeline.py
ax/models/__init__.py
ax/models/fix.py
ax/models/issue.py
ax/models/result.py
ax/services/__init__.py
ax/services/ai_config.py
ax/services/llm_service.py
ax/strategies/__init__.py
ax/strategies/base.py
ax/strategies/docstring.py
ax/strategies/error_handling.py
ax/strategies/imports.py
ax/strategies/logical_errors.py
ax/strategies/naming.py
ax/strategies/performance.py
ax/strategies/security.py
ax/strategies/type_hints.py
ax/utils/__init__.py
ax/utils/file_utils.py
ax/utils/hash_utils.py
ax_consistency-0.1.0.dist-info/METADATA
ax_consistency-0.1.0.dist-info/WHEEL
ax_consistency-0.1.0.dist-info/entry_points.txt
ax_consistency-0.1.0.dist-info/top_level.txt
ax_consistency-0.1.0.dist-info/RECORD
