Metadata-Version: 2.4
Name: ax-consistency
Version: 0.1.0
Summary: AI-powered code consistency checker and fixer for multiple languages
Author-email: CAVELAB-HK <contact@cavelab.dev>
License: MIT
Project-URL: Homepage, https://github.com/CAVELAB-HK/AX
Project-URL: Repository, https://github.com/CAVELAB-HK/AX.git
Project-URL: Issues, https://github.com/CAVELAB-HK/AX/issues
Classifier: Development Status :: 3 - Alpha
Classifier: Intended Audience :: Developers
Classifier: License :: OSI Approved :: MIT License
Classifier: Programming Language :: Python :: 3
Classifier: Programming Language :: Python :: 3.8
Classifier: Programming Language :: Python :: 3.9
Classifier: Programming Language :: Python :: 3.10
Classifier: Programming Language :: Python :: 3.11
Classifier: Topic :: Software Development :: Quality Assurance
Classifier: Topic :: Software Development :: Code Generators
Requires-Python: >=3.8
Requires-Dist: typer>=0.9.0
Requires-Dist: rich>=13.0.0
Requires-Dist: watchdog>=3.0.0
Requires-Dist: toml>=0.10.2
Requires-Dist: python-dotenv>=1.0.0
Requires-Dist: requests>=2.31.0
Provides-Extra: dev
Requires-Dist: pytest>=7.0.0; extra == "dev"
Requires-Dist: black>=23.0.0; extra == "dev"
Requires-Dist: isort>=5.12.0; extra == "dev"
Requires-Dist: mypy>=1.0.0; extra == "dev"
